[
  {
    "otitle": "(T_N) SHIFFER - Her, Endlessly _ SIAMESE",
    "artist": "SHIFFER",
    "title": "SHIFFER - Her, Endlessly",
    "genre": "T_N",
    "label": "SIAMESE",
    "time": "2021-12-03T00:03:58"
  },
  {
    "otitle": "(E) NOSAJ THING - nowhere",
    "artist": "NOSAJ THING",
    "title": "nowhere",
    "genre": "E",
    "label": "",
    "time": "2021-12-03T00:11:31"
  },
  {
    "otitle": "(J) VISTA LE VIE - skunkogram F COMM",
    "artist": "VISTA LE VIE",
    "title": "skunkogram",
    "genre": "J",
    "label": "F COMM",
    "time": "2021-12-03T00:13:56"
  },
  {
    "otitle": "PBB - Luckily We Still Have Music",
    "artist": "PBB",
    "title": "Luckily We Still Have Music",
    "genre": "BB - Luckily We Still Have Musi",
    "label": "",
    "time": "2021-12-03T00:20:44"
  },
  {
    "otitle": "(H_N) MONOLITHIC - time",
    "artist": "MONOLITHIC",
    "title": "time",
    "genre": "H_N",
    "label": "",
    "time": "2021-12-03T00:21:02"
  },
  {
    "otitle": "(t_N) sniper mode - bulletproof",
    "artist": "sniper mode",
    "title": "bulletproof",
    "genre": "t_N",
    "label": "",
    "time": "2021-12-03T00:27:40"
  },
  {
    "otitle": "(Db_N) THE GREEN MAN - chain smoker",
    "artist": "THE GREEN MAN",
    "title": "chain smoker",
    "genre": "Db_N",
    "label": "",
    "time": "2021-12-03T00:33:57"
  },
  {
    "otitle": "(E) TOH IMAGO - ... ( rRoxymore rRemix)",
    "artist": "TOH IMAGO",
    "title": "... ( rRoxymore rRemix)",
    "genre": "E",
    "label": "",
    "time": "2021-12-03T00:40:31"
  },
  {
    "otitle": "(T_N) SO KOBAYASHI - ascension",
    "artist": "SO KOBAYASHI",
    "title": "ascension",
    "genre": "T_N",
    "label": "",
    "time": "2021-12-03T00:47:06"
  },
  {
    "otitle": "PBB - Luckily We Still Have Music",
    "artist": "PBB",
    "title": "Luckily We Still Have Music",
    "genre": "BB - Luckily We Still Have Musi",
    "label": "",
    "time": "2021-12-03T00:53:54"
  },
  {
    "otitle": "(Db_N) SOLSAN BAZIL MC - Follow _ VANDAL LTD",
    "artist": "SOLSAN BAZIL MC",
    "title": "SOLSAN BAZIL MC - Follow",
    "genre": "Db_N",
    "label": "VANDAL LTD",
    "time": "2021-12-03T00:54:06"
  },
  {
    "otitle": "(Bra_Db) DRUMAGICK - sambarock",
    "artist": "DRUMAGICK",
    "title": "sambarock",
    "genre": "Bra_Db",
    "label": "",
    "time": "2021-12-03T00:58:50"
  },
  {
    "otitle": "(H_N) MOIRE - Know Me _ HYPERCOLOUR",
    "artist": "MOIRE",
    "title": "MOIRE - Know Me",
    "genre": "H_N",
    "label": "HYPERCOLOUR",
    "time": "2021-12-03T01:02:50"
  },
  {
    "otitle": "(T_N) EDUARDO DE LA CALLE - Tanzbaren Elemente",
    "artist": "EDUARDO DE LA CALLE",
    "title": "Tanzbaren Elemente",
    "genre": "T_N",
    "label": "",
    "time": "2021-12-03T01:07:01"
  },
  {
    "otitle": "(E) APHEX TWIN - t69 collapse",
    "artist": "APHEX TWIN",
    "title": "t69 collapse",
    "genre": "E",
    "label": "",
    "time": "2021-12-03T01:14:00"
  },
  {
    "otitle": "(Jup) BIG MAYBELLE - i've got a feelin'",
    "artist": "BIG MAYBELLE",
    "title": "i've got a feelin'",
    "genre": "Jup",
    "label": "",
    "time": "2021-12-03T01:19:20"
  },
  {
    "otitle": "PBB - Luckily We Still Have Music",
    "artist": "PBB",
    "title": "Luckily We Still Have Music",
    "genre": "BB - Luckily We Still Have Musi",
    "label": "",
    "time": "2021-12-03T01:22:11"
  },
  {
    "otitle": "(H_N) ZITO MOWA - Sumthng More",
    "artist": "ZITO MOWA",
    "title": "Sumthng More",
    "genre": "H_N",
    "label": "",
    "time": "2021-12-03T01:22:40"
  },
  {
    "otitle": "(T_N) SOUNDBED - Turnaround  (Pezzner 30 Watt Mix)",
    "artist": "SOUNDBED",
    "title": "Turnaround  (Pezzner 30 Watt Mix)",
    "genre": "T_N",
    "label": "",
    "time": "2021-12-03T01:28:29"
  },
  {
    "otitle": "(H_N) WHATIF - deapsea",
    "artist": "WHATIF",
    "title": "deapsea",
    "genre": "H_N",
    "label": "",
    "time": "2021-12-03T01:35:12"
  },
  {
    "otitle": "(E) TIPPER  - supersport FUEL",
    "artist": "TIPPER",
    "title": "supersport",
    "genre": "E",
    "label": "FUEL",
    "time": "2021-12-03T01:40:43"
  },
  {
    "otitle": "(T_N) southern outpost - characteristics ep",
    "artist": "southern outpost",
    "title": "characteristics ep",
    "genre": "T_N",
    "label": "",
    "time": "2021-12-03T01:44:02"
  },
  {
    "otitle": "PBB - Luckily We Still Have Music",
    "artist": "PBB",
    "title": "Luckily We Still Have Music",
    "genre": "BB - Luckily We Still Have Musi",
    "label": "",
    "time": "2021-12-03T01:50:25"
  },
  {
    "otitle": "(H_N) MAR ONE X LPACA - Be _ WANG",
    "artist": "MAR ONE X LPACA",
    "title": "MAR ONE X LPACA - Be",
    "genre": "H_N",
    "label": "WANG",
    "time": "2021-12-03T01:50:38"
  },
  {
    "otitle": "(Ra) PLIERS - bam bam",
    "artist": "PLIERS",
    "title": "bam bam",
    "genre": "Ra",
    "label": "",
    "time": "2021-12-03T01:53:39"
  },
  {
    "otitle": "(H_N) STEPHANE ATTIAS - Fairy Tales _ VISIONS",
    "artist": "STEPHANE ATTIAS",
    "title": "STEPHANE ATTIAS - Fairy Tales",
    "genre": "H_N",
    "label": "VISIONS",
    "time": "2021-12-03T01:57:44"
  },
  {
    "otitle": "(T_N) CITY 2 CITY - True People _ METROHM",
    "artist": "CITY 2 CITY",
    "title": "CITY 2 CITY - True People",
    "genre": "T_N",
    "label": "METROHM",
    "time": "2021-12-03T02:03:56"
  },
  {
    "otitle": "(E) TIPPER - reality harshness defender",
    "artist": "TIPPER",
    "title": "reality harshness defender",
    "genre": "E",
    "label": "",
    "time": "2021-12-03T02:12:17"
  },
  {
    "otitle": "(J) ARCHIE SHEPP & JEANNE LEE - blas\u00e9",
    "artist": "ARCHIE SHEPP & JEANNE LEE",
    "title": "blas\u00e9",
    "genre": "J",
    "label": "",
    "time": "2021-12-03T02:17:13"
  },
  {
    "otitle": "PBB - Luckily We Still Have Music",
    "artist": "PBB",
    "title": "Luckily We Still Have Music",
    "genre": "BB - Luckily We Still Have Musi",
    "label": "",
    "time": "2021-12-03T02:27:35"
  },
  {
    "otitle": "(H_N) LUIS RADIO - The Pink Suitcase",
    "artist": "LUIS RADIO",
    "title": "The Pink Suitcase",
    "genre": "H_N",
    "label": "",
    "time": "2021-12-03T02:27:53"
  },
  {
    "otitle": "(t_N) the connection machine - harmonic resonance",
    "artist": "the connection machine",
    "title": "harmonic resonance",
    "genre": "t_N",
    "label": "",
    "time": "2021-12-03T02:34:51"
  },
  {
    "otitle": "(h_N) LUISITO QUINTERO - gbagada",
    "artist": "LUISITO QUINTERO",
    "title": "gbagada",
    "genre": "h_N",
    "label": "",
    "time": "2021-12-03T02:42:29"
  },
  {
    "otitle": "(E) KUF - humane",
    "artist": "KUF",
    "title": "humane",
    "genre": "E",
    "label": "",
    "time": "2021-12-03T02:50:28"
  },
  {
    "otitle": "(T_N) TECWAA - remember the clear light",
    "artist": "TECWAA",
    "title": "remember the clear light",
    "genre": "T_N",
    "label": "",
    "time": "2021-12-03T02:54:31"
  },
  {
    "otitle": "PBB - Luckily We Still Have Music",
    "artist": "PBB",
    "title": "Luckily We Still Have Music",
    "genre": "BB - Luckily We Still Have Musi",
    "label": "",
    "time": "2021-12-03T03:02:10"
  },
  {
    "otitle": "(E_N) FELIX DA HOUSECAT & BLAKK HAZEL & DAVE THE HUSTLER - Vin Rouge _",
    "artist": "FELIX DA HOUSECAT & BLAKK HAZEL & DAVE THE HUSTLER",
    "title": "",
    "genre": "E_N",
    "label": "",
    "time": "2021-12-03T03:02:16"
  },
  {
    "otitle": "(Bra) VERA - Vera  Sambinha",
    "artist": "VERA",
    "title": "Vera  Sambinha",
    "genre": "Bra",
    "label": "",
    "time": "2021-12-03T03:05:16"
  },
  {
    "otitle": "(H_N) MAYFLO - I Miss Tap Water Jams _ CHINEURS DE HOUSE",
    "artist": "MAYFLO",
    "title": "MAYFLO - I Miss Tap Water Jams",
    "genre": "H_N",
    "label": "CHINEURS DE HOUSE",
    "time": "2021-12-03T03:08:27"
  },
  {
    "otitle": "(T_N) E ARTIST - Illusory Image (Legendary Paradox Remix)",
    "artist": "E ARTIST",
    "title": "Illusory Image (Legendary Paradox Remix)",
    "genre": "T_N",
    "label": "",
    "time": "2021-12-03T03:13:18"
  },
  {
    "otitle": "(Dt) TOMMY GUERRERO - so blue it s black GALAXIA",
    "artist": "TOMMY GUERRERO",
    "title": "so blue it s black",
    "genre": "Dt",
    "label": "GALAXIA",
    "time": "2021-12-03T03:18:36"
  },
  {
    "otitle": "(J) KABUKI - tempest CLIMATE",
    "artist": "KABUKI",
    "title": "tempest",
    "genre": "J",
    "label": "CLIMATE",
    "time": "2021-12-03T03:22:05"
  },
  {
    "otitle": "PBB - Luckily We Still Have Music",
    "artist": "PBB",
    "title": "Luckily We Still Have Music",
    "genre": "BB - Luckily We Still Have Musi",
    "label": "",
    "time": "2021-12-03T03:28:34"
  },
  {
    "otitle": "(H_N) AWATO 3 - the wall",
    "artist": "AWATO 3",
    "title": "the wall",
    "genre": "H_N",
    "label": "",
    "time": "2021-12-03T03:28:41"
  },
  {
    "otitle": "(T_N) JOEY ANDERSON - archer's ceremony",
    "artist": "JOEY ANDERSON",
    "title": "archer's ceremony",
    "genre": "T_N",
    "label": "",
    "time": "2021-12-03T03:34:44"
  },
  {
    "otitle": "(H_N) ANDREA OLIVA - the fifth river",
    "artist": "ANDREA OLIVA",
    "title": "the fifth river",
    "genre": "H_N",
    "label": "",
    "time": "2021-12-03T03:41:25"
  },
  {
    "otitle": "(E) AGORIA - heart beating",
    "artist": "AGORIA",
    "title": "heart beating",
    "genre": "E",
    "label": "",
    "time": "2021-12-03T03:46:45"
  },
  {
    "otitle": "(T_N) JORI HULKONEN - my brother went to space ...",
    "artist": "JORI HULKONEN",
    "title": "my brother went to space ...",
    "genre": "T_N",
    "label": "",
    "time": "2021-12-03T03:52:06"
  },
  {
    "otitle": "PBB - Luckily We Still Have Music",
    "artist": "PBB",
    "title": "Luckily We Still Have Music",
    "genre": "BB - Luckily We Still Have Musi",
    "label": "",
    "time": "2021-12-03T04:00:14"
  },
  {
    "otitle": "(H_N) HARRY WOLFMAN - Upstream (2021 Version) _ TOY TONICS",
    "artist": "HARRY WOLFMAN",
    "title": "HARRY WOLFMAN - Upstream (2021 Version)",
    "genre": "H_N",
    "label": "TOY TONICS",
    "time": "2021-12-03T04:00:37"
  },
  {
    "otitle": "(W) HOODNA ORCHESTRA - Ofel I",
    "artist": "HOODNA ORCHESTRA",
    "title": "Ofel",
    "genre": "W",
    "label": "I",
    "time": "2021-12-03T04:05:45"
  },
  {
    "otitle": "(T_N) VINCE WATSON - Second Wave (John Beltran's Pan Am Remix)",
    "artist": "VINCE WATSON",
    "title": "Second Wave (John Beltran's Pan Am Remix)",
    "genre": "T_N",
    "label": "",
    "time": "2021-12-03T04:09:56"
  },
  {
    "otitle": "(H_N) JONNA - Jus Move _ LUMBERJACKS IN HELL",
    "artist": "JONNA",
    "title": "JONNA - Jus Move",
    "genre": "H_N",
    "label": "LUMBERJACKS IN HELL",
    "time": "2021-12-03T04:17:30"
  },
  {
    "otitle": "(E) PLON - many hours passed",
    "artist": "PLON",
    "title": "many hours passed",
    "genre": "E",
    "label": "",
    "time": "2021-12-03T04:22:50"
  },
  {
    "otitle": "(J) SOM 3 - margarida b",
    "artist": "SOM 3",
    "title": "margarida b",
    "genre": "J",
    "label": "",
    "time": "2021-12-03T04:29:56"
  },
  {
    "otitle": "PBB - Luckily We Still Have Music",
    "artist": "PBB",
    "title": "Luckily We Still Have Music",
    "genre": "BB - Luckily We Still Have Musi",
    "label": "",
    "time": "2021-12-03T04:33:02"
  },
  {
    "otitle": "(T_N) FLORENCE - a touch of heaven",
    "artist": "FLORENCE",
    "title": "a touch of heaven",
    "genre": "T_N",
    "label": "",
    "time": "2021-12-03T04:33:31"
  },
  {
    "otitle": "(T_N) SMAK - in the beginning (Ian O'Donovan Remix)",
    "artist": "SMAK",
    "title": "in the beginning (Ian O'Donovan Remix)",
    "genre": "T_N",
    "label": "",
    "time": "2021-12-03T04:42:44"
  },
  {
    "otitle": "(H_N) MOONSTAR - String Theory",
    "artist": "MOONSTAR",
    "title": "String Theory",
    "genre": "H_N",
    "label": "",
    "time": "2021-12-03T04:51:29"
  },
  {
    "otitle": "(Dt) TOSCA - fuck dub pt 1 & 2",
    "artist": "TOSCA",
    "title": "fuck dub pt 1 & 2",
    "genre": "Dt",
    "label": "",
    "time": "2021-12-03T04:58:04"
  },
  {
    "otitle": "(T_N) SYSTEM 7 - alpha wave (Plastikman rmx)",
    "artist": "SYSTEM 7",
    "title": "alpha wave (Plastikman rmx)",
    "genre": "T_N",
    "label": "",
    "time": "2021-12-03T05:06:42"
  },
  {
    "otitle": "PBB - Luckily We Still Have Music",
    "artist": "PBB",
    "title": "Luckily We Still Have Music",
    "genre": "BB - Luckily We Still Have Musi",
    "label": "",
    "time": "2021-12-03T05:26:15"
  },
  {
    "otitle": "(H_N) MOODYMANN - Keep On Coming _ CIRCOLOCO",
    "artist": "MOODYMANN",
    "title": "MOODYMANN - Keep On Coming",
    "genre": "H_N",
    "label": "CIRCOLOCO",
    "time": "2021-12-03T05:26:44"
  },
  {
    "otitle": "(L) MAXIMO RODRIGUEZ - mambalogia",
    "artist": "MAXIMO RODRIGUEZ",
    "title": "mambalogia",
    "genre": "L",
    "label": "",
    "time": "2021-12-03T05:31:53"
  },
  {
    "otitle": "(T_N) KARIM KAHAR - Collage _MESMA",
    "artist": "KARIM KAHAR",
    "title": "KARIM KAHAR - Collage",
    "genre": "T_N",
    "label": "MESMA",
    "time": "2021-12-03T05:35:52"
  },
  {
    "otitle": "(T_N) ANTHONY ROTHER - The Ccm Corporation _ PSI",
    "artist": "ANTHONY ROTHER",
    "title": "ANTHONY ROTHER - The Ccm Corporation",
    "genre": "T_N",
    "label": "PSI",
    "time": "2021-12-03T05:42:20"
  },
  {
    "otitle": "(E) SAO PARIS - envie de",
    "artist": "SAO PARIS",
    "title": "envie de",
    "genre": "E",
    "label": "",
    "time": "2021-12-03T05:49:03"
  },
  {
    "otitle": "(J_Bb) RUSS GABRIEL - offenbach west OUT OF THE LOOP",
    "artist": "RUSS GABRIEL",
    "title": "offenbach west",
    "genre": "J_Bb",
    "label": "OUT OF THE LOOP",
    "time": "2021-12-03T05:53:00"
  },
  {
    "otitle": "PBB - Luckily We Still Have Music",
    "artist": "PBB",
    "title": "Luckily We Still Have Music",
    "genre": "BB - Luckily We Still Have Musi",
    "label": "",
    "time": "2021-12-03T05:58:43"
  },
  {
    "otitle": "(J_N) 23 SKIDOO - mary's operation",
    "artist": "23 SKIDOO",
    "title": "mary's operation",
    "genre": "J_N",
    "label": "",
    "time": "2021-12-03T05:59:01"
  },
  {
    "otitle": "(HH) THE BUG - Bang _ NINJA TUNE",
    "artist": "THE BUG",
    "title": "THE BUG - Bang",
    "genre": "HH",
    "label": "NINJA TUNE",
    "time": "2021-12-03T06:09:07"
  },
  {
    "otitle": "PBB - Luckily We Still Have Music",
    "artist": "PBB",
    "title": "Luckily We Still Have Music",
    "genre": "BB - Luckily We Still Have Musi",
    "label": "",
    "time": "2021-12-03T06:12:02"
  },
  {
    "otitle": "(S) THE FABULOUS THREE - nightbird",
    "artist": "THE FABULOUS THREE",
    "title": "nightbird",
    "genre": "S",
    "label": "",
    "time": "2021-12-03T06:12:20"
  },
  {
    "otitle": "(Maghreb) MERCAN DEDE - velfaname RH POZITIF MUZIK",
    "artist": "MERCAN DEDE",
    "title": "velfaname",
    "genre": "Maghreb",
    "label": "RH POZITIF MUZIK",
    "time": "2021-12-03T06:14:23"
  },
  {
    "otitle": "(H) THE BELOVED - the sun rising",
    "artist": "THE BELOVED",
    "title": "the sun rising",
    "genre": "H",
    "label": "",
    "time": "2021-12-03T06:21:04"
  },
  {
    "otitle": "(T_N) FRITZ KALKBRENNER - dead end",
    "artist": "FRITZ KALKBRENNER",
    "title": "dead end",
    "genre": "T_N",
    "label": "",
    "time": "2021-12-03T06:26:17"
  },
  {
    "otitle": "(Dt) MAKULA - never",
    "artist": "MAKULA",
    "title": "never",
    "genre": "Dt",
    "label": "",
    "time": "2021-12-03T06:33:39"
  },
  {
    "otitle": "(N_N) MAVIS STAPLES - we shall not be moved",
    "artist": "MAVIS STAPLES",
    "title": "we shall not be moved",
    "genre": "N_N",
    "label": "",
    "time": "2021-12-03T06:36:58"
  },
  {
    "otitle": "(S) THE ELGINS - darling baby",
    "artist": "THE ELGINS",
    "title": "darling baby",
    "genre": "S",
    "label": "",
    "time": "2021-12-03T06:41:26"
  },
  {
    "otitle": "(J) COUNT BASIE - jumpin at the wodside",
    "artist": "COUNT BASIE",
    "title": "jumpin at the wodside",
    "genre": "J",
    "label": "",
    "time": "2021-12-03T06:44:16"
  },
  {
    "otitle": "PBB - Luckily We Still Have Music",
    "artist": "PBB",
    "title": "Luckily We Still Have Music",
    "genre": "BB - Luckily We Still Have Musi",
    "label": "",
    "time": "2021-12-03T06:47:34"
  },
  {
    "otitle": "(Ro_N) YPPAH - almost in that category",
    "artist": "YPPAH",
    "title": "almost in that category",
    "genre": "Ro_N",
    "label": "",
    "time": "2021-12-03T06:47:52"
  },
  {
    "otitle": "(Ro) STRANGE BOYS - be brave",
    "artist": "STRANGE BOYS",
    "title": "be brave",
    "genre": "Ro",
    "label": "",
    "time": "2021-12-03T06:51:39"
  },
  {
    "otitle": "(H) RIVA STARR - The Feeling (Deetron Keys Remix) _ Snatch",
    "artist": "RIVA STARR",
    "title": "RIVA STARR - The Feeling (Deetron Keys Remix)",
    "genre": "H",
    "label": "Snatch",
    "time": "2021-12-03T06:54:33"
  },
  {
    "otitle": "PBB - Luckily We Still Have Music",
    "artist": "PBB",
    "title": "Luckily We Still Have Music",
    "genre": "BB - Luckily We Still Have Musi",
    "label": "",
    "time": "2021-12-03T07:00:16"
  },
  {
    "otitle": "(D_N) MILDIOU_ - de_natura_rerum_",
    "artist": "MILDIOU_",
    "title": "de_natura_rerum_",
    "genre": "D_N",
    "label": "",
    "time": "2021-12-03T07:00:28"
  },
  {
    "otitle": "(F) MATATA - i feel funky",
    "artist": "MATATA",
    "title": "i feel funky",
    "genre": "F",
    "label": "",
    "time": "2021-12-03T07:06:51"
  },
  {
    "otitle": "(H_N) GREGORY - s 2",
    "artist": "GREGORY",
    "title": "s 2",
    "genre": "H_N",
    "label": "",
    "time": "2021-12-03T07:09:46"
  },
  {
    "otitle": "(H) UNKNOWN ARTIST - mawonder",
    "artist": "UNKNOWN ARTIST",
    "title": "mawonder",
    "genre": "H",
    "label": "",
    "time": "2021-12-03T07:19:39"
  },
  {
    "otitle": "(E) LAURENT GARNIER - 9.01 9.06 _ F COMMUNICATIONS",
    "artist": "LAURENT GARNIER",
    "title": "LAURENT GARNIER - 9.01 9.06",
    "genre": "E",
    "label": "F COMMUNICATIONS",
    "time": "2021-12-03T07:27:42"
  },
  {
    "otitle": "(P) TINDERSTICKS - a night in QUICKSILVER",
    "artist": "TINDERSTICKS",
    "title": "a night in",
    "genre": "P",
    "label": "QUICKSILVER",
    "time": "2021-12-03T07:33:06"
  },
  {
    "otitle": "(Balkan) DONA DUMITRU SIMINICA - de trei ani nu dau pe acasa",
    "artist": "DONA DUMITRU SIMINICA",
    "title": "de trei ani nu dau pe acasa",
    "genre": "Balkan",
    "label": "",
    "time": "2021-12-03T07:39:30"
  },
  {
    "otitle": "(Balkan) DONA DUMITRU SIMINICA - de trei ani nu dau pe acasa",
    "artist": "DONA DUMITRU SIMINICA",
    "title": "de trei ani nu dau pe acasa",
    "genre": "Balkan",
    "label": "",
    "time": "2021-12-03T07:43:37"
  },
  {
    "otitle": "(Fr_R_N) SERGE GAINSBOURG - brigade des stups (Dub Style)",
    "artist": "SERGE GAINSBOURG",
    "title": "brigade des stups (Dub Style)",
    "genre": "Fr_R_N",
    "label": "",
    "time": "2021-12-03T07:44:01"
  },
  {
    "otitle": "PBB - Luckily We Still Have Music",
    "artist": "PBB",
    "title": "Luckily We Still Have Music",
    "genre": "BB - Luckily We Still Have Musi",
    "label": "",
    "time": "2021-12-03T07:46:03"
  },
  {
    "otitle": "(J) OLLI AHVENLATHI - grandma's rocking chair",
    "artist": "OLLI AHVENLATHI",
    "title": "grandma's rocking chair",
    "genre": "J",
    "label": "",
    "time": "2021-12-03T07:46:38"
  },
  {
    "otitle": "(HH_Fr) NEKFEU - mal aime",
    "artist": "NEKFEU",
    "title": "mal aime",
    "genre": "HH_Fr",
    "label": "",
    "time": "2021-12-03T07:52:03"
  },
  {
    "otitle": "(H) LOWPAZZ - good old days (Shur",
    "artist": "LOWPAZZ",
    "title": "good old days (Shur",
    "genre": "H",
    "label": "",
    "time": "2021-12-03T07:55:55"
  },
  {
    "otitle": "(H) LOWPAZZ - good old days (Shur",
    "artist": "LOWPAZZ",
    "title": "good old days (Shur",
    "genre": "H",
    "label": "",
    "time": "2021-12-03T07:58:36"
  },
  {
    "otitle": "(T) MERV - Rechord _ RELEASE SUSTAIN",
    "artist": "MERV",
    "title": "MERV - Rechord",
    "genre": "T",
    "label": "RELEASE SUSTAIN",
    "time": "2021-12-03T08:02:35"
  },
  {
    "otitle": "PBB - Luckily We Still Have Music",
    "artist": "PBB",
    "title": "Luckily We Still Have Music",
    "genre": "BB - Luckily We Still Have Musi",
    "label": "",
    "time": "2021-12-03T08:09:25"
  },
  {
    "otitle": "(S) BOOZOU_BAJOU_ - Sign_",
    "artist": "BOOZOU_BAJOU_",
    "title": "Sign_",
    "genre": "S",
    "label": "",
    "time": "2021-12-03T08:09:55"
  },
  {
    "otitle": "(W) ARAT KILO - . madala",
    "artist": "ARAT KILO",
    "title": ". madala",
    "genre": "W",
    "label": "",
    "time": "2021-12-03T08:15:36"
  },
  {
    "otitle": "(H) THE FITNESS & PONY - pretty muthafucka",
    "artist": "THE FITNESS & PONY",
    "title": "pretty muthafucka",
    "genre": "H",
    "label": "",
    "time": "2021-12-03T08:20:36"
  },
  {
    "otitle": "(T_N) LOVE YOU - Nelly",
    "artist": "LOVE YOU",
    "title": "Nelly",
    "genre": "T_N",
    "label": "",
    "time": "2021-12-03T08:26:51"
  },
  {
    "otitle": "(T_N) LOVE YOU - Nelly",
    "artist": "LOVE YOU",
    "title": "Nelly",
    "genre": "T_N",
    "label": "",
    "time": "2021-12-03T08:31:56"
  },
  {
    "otitle": "(E) EPROM - oksana (Ivy Lab Remix)",
    "artist": "EPROM",
    "title": "oksana (Ivy Lab Remix)",
    "genre": "E",
    "label": "",
    "time": "2021-12-03T08:33:01"
  },
  {
    "otitle": "(E_N) SNORETX - strange aeons",
    "artist": "SNORETX",
    "title": "strange aeons",
    "genre": "E_N",
    "label": "",
    "time": "2021-12-03T08:36:46"
  },
  {
    "otitle": "(E_N) SNORETX - strange aeons",
    "artist": "SNORETX",
    "title": "strange aeons",
    "genre": "E_N",
    "label": "",
    "time": "2021-12-03T08:42:21"
  },
  {
    "otitle": "(F) S O U L - tell it like it is",
    "artist": "S O U L",
    "title": "tell it like it is",
    "genre": "F",
    "label": "",
    "time": "2021-12-03T08:42:51"
  },
  {
    "otitle": "(J) EMANATIVE - Reflection",
    "artist": "EMANATIVE",
    "title": "Reflection",
    "genre": "J",
    "label": "",
    "time": "2021-12-03T08:47:11"
  },
  {
    "otitle": "PBB - Luckily We Still Have Music",
    "artist": "PBB",
    "title": "Luckily We Still Have Music",
    "genre": "BB - Luckily We Still Have Musi",
    "label": "",
    "time": "2021-12-03T08:54:10"
  },
  {
    "otitle": "(P_N) DJ FOOD - all covered in darkness part 1",
    "artist": "DJ FOOD",
    "title": "all covered in darkness part 1",
    "genre": "P_N",
    "label": "",
    "time": "2021-12-03T08:54:28"
  },
  {
    "otitle": "(P) TITANIC - sultana",
    "artist": "TITANIC",
    "title": "sultana",
    "genre": "P",
    "label": "",
    "time": "2021-12-03T08:58:52"
  },
  {
    "otitle": "(S) YAYA BEY - we'll skate soon _ BIG DADA",
    "artist": "YAYA BEY",
    "title": "YAYA BEY - we'll skate soon",
    "genre": "S",
    "label": "BIG DADA",
    "time": "2021-12-03T09:03:05"
  },
  {
    "otitle": "PBB - Luckily We Still Have Music",
    "artist": "PBB",
    "title": "Luckily We Still Have Music",
    "genre": "BB - Luckily We Still Have Musi",
    "label": "",
    "time": "2021-12-03T09:06:21"
  },
  {
    "otitle": "(F_N) ODDISEE - brea",
    "artist": "ODDISEE",
    "title": "brea",
    "genre": "F_N",
    "label": "",
    "time": "2021-12-03T09:06:39"
  },
  {
    "otitle": "(S) THE TOMANGOES - I Really Love You",
    "artist": "THE TOMANGOES",
    "title": "I Really Love You",
    "genre": "S",
    "label": "",
    "time": "2021-12-03T09:11:44"
  },
  {
    "otitle": "(T_N) UMWELT - secret of a black world",
    "artist": "UMWELT",
    "title": "secret of a black world",
    "genre": "T_N",
    "label": "",
    "time": "2021-12-03T09:13:46"
  },
  {
    "otitle": "(H) GUILLAUME & THE COUTU DUMONTS - ubiquitous gaze",
    "artist": "GUILLAUME & THE COUTU DUMONTS",
    "title": "ubiquitous gaze",
    "genre": "H",
    "label": "",
    "time": "2021-12-03T09:19:02"
  },
  {
    "otitle": "(Dt) MASSIVE ATTACK - teardrops CIRCA",
    "artist": "MASSIVE ATTACK",
    "title": "teardrops",
    "genre": "Dt",
    "label": "CIRCA",
    "time": "2021-12-03T09:29:32"
  },
  {
    "otitle": "(X) ROY BUDD - get carter",
    "artist": "ROY BUDD",
    "title": "get carter",
    "genre": "X",
    "label": "",
    "time": "2021-12-03T09:35:01"
  },
  {
    "otitle": "(L) LA LUPE - fever",
    "artist": "LA LUPE",
    "title": "fever",
    "genre": "L",
    "label": "",
    "time": "2021-12-03T09:38:18"
  },
  {
    "otitle": "(F_E_N) ARCADION - radar station 8",
    "artist": "ARCADION",
    "title": "radar station 8",
    "genre": "F_E_N",
    "label": "",
    "time": "2021-12-03T09:41:05"
  },
  {
    "otitle": "PBB - Luckily We Still Have Music",
    "artist": "PBB",
    "title": "Luckily We Still Have Music",
    "genre": "BB - Luckily We Still Have Musi",
    "label": "",
    "time": "2021-12-03T09:44:26"
  },
  {
    "otitle": "(J) THE STANCE BROTHERS - steve mc queen",
    "artist": "THE STANCE BROTHERS",
    "title": "steve mc queen",
    "genre": "J",
    "label": "",
    "time": "2021-12-03T09:45:13"
  },
  {
    "otitle": "(HH) BLU & EXILE - another day",
    "artist": "BLU & EXILE",
    "title": "another day",
    "genre": "HH",
    "label": "",
    "time": "2021-12-03T09:48:35"
  },
  {
    "otitle": "(H) PIXEL - people need people",
    "artist": "PIXEL",
    "title": "people need people",
    "genre": "H",
    "label": "",
    "time": "2021-12-03T09:52:29"
  },
  {
    "otitle": "(H) PIXEL - people need people",
    "artist": "PIXEL",
    "title": "people need people",
    "genre": "H",
    "label": "",
    "time": "2021-12-03T09:55:23"
  },
  {
    "otitle": "(H) DJ DEEP - Batu",
    "artist": "DJ DEEP",
    "title": "Batu",
    "genre": "H",
    "label": "",
    "time": "2021-12-03T09:59:07"
  },
  {
    "otitle": "PBB - Luckily We Still Have Music",
    "artist": "PBB",
    "title": "Luckily We Still Have Music",
    "genre": "BB - Luckily We Still Have Musi",
    "label": "",
    "time": "2021-12-03T10:05:12"
  },
  {
    "otitle": "(F) MILEZ_BENJIMAN_ - our_house_",
    "artist": "MILEZ_BENJIMAN_",
    "title": "our_house_",
    "genre": "F",
    "label": "",
    "time": "2021-12-03T10:05:41"
  },
  {
    "otitle": "(R) HORACE ANDY - evilest thing",
    "artist": "HORACE ANDY",
    "title": "evilest thing",
    "genre": "R",
    "label": "",
    "time": "2021-12-03T10:12:05"
  },
  {
    "otitle": "(H) KEVIN IRVING - ride the rhythm TRAX",
    "artist": "KEVIN IRVING",
    "title": "ride the rhythm",
    "genre": "H",
    "label": "TRAX",
    "time": "2021-12-03T10:14:47"
  },
  {
    "otitle": "(H_N) THE GREEN MEN - blink",
    "artist": "THE GREEN MEN",
    "title": "blink",
    "genre": "H_N",
    "label": "",
    "time": "2021-12-03T10:20:05"
  },
  {
    "otitle": "(H_N) THE GREEN MEN - blink",
    "artist": "THE GREEN MEN",
    "title": "blink",
    "genre": "H_N",
    "label": "",
    "time": "2021-12-03T10:30:44"
  },
  {
    "otitle": "(Dt) PRIMAL SCREAM - loaded",
    "artist": "PRIMAL SCREAM",
    "title": "loaded",
    "genre": "Dt",
    "label": "",
    "time": "2021-12-03T10:31:18"
  },
  {
    "otitle": "(dt_N) daft punk - make love",
    "artist": "daft punk",
    "title": "make love",
    "genre": "dt_N",
    "label": "",
    "time": "2021-12-03T10:35:50"
  },
  {
    "otitle": "(F) LOVE DROP - the affair",
    "artist": "LOVE DROP",
    "title": "the affair",
    "genre": "F",
    "label": "",
    "time": "2021-12-03T10:40:33"
  },
  {
    "otitle": "(J) BUILDING AN ARK - conversations",
    "artist": "BUILDING AN ARK",
    "title": "conversations",
    "genre": "J",
    "label": "",
    "time": "2021-12-03T10:47:12"
  },
  {
    "otitle": "PBB - Luckily We Still Have Music",
    "artist": "PBB",
    "title": "Luckily We Still Have Music",
    "genre": "BB - Luckily We Still Have Musi",
    "label": "",
    "time": "2021-12-03T10:52:31"
  },
  {
    "otitle": "(P_N) FLOBOTS_ - Handlebars_",
    "artist": "FLOBOTS_",
    "title": "Handlebars_",
    "genre": "P_N",
    "label": "",
    "time": "2021-12-03T10:52:42"
  },
  {
    "otitle": "(Folk) BONNIE PRINCE BILLY - new whaling",
    "artist": "BONNIE PRINCE BILLY",
    "title": "new whaling",
    "genre": "Folk",
    "label": "",
    "time": "2021-12-03T10:55:52"
  },
  {
    "otitle": "(S) JORDAN RAKEI - Family _ NINJA TUNE",
    "artist": "JORDAN RAKEI",
    "title": "JORDAN RAKEI - Family",
    "genre": "S",
    "label": "NINJA TUNE",
    "time": "2021-12-03T11:01:23"
  },
  {
    "otitle": "PBB - Luckily We Still Have Music",
    "artist": "PBB",
    "title": "Luckily We Still Have Music",
    "genre": "BB - Luckily We Still Have Musi",
    "label": "",
    "time": "2021-12-03T11:04:46"
  },
  {
    "otitle": "(H) SKWERL - you need to dance",
    "artist": "SKWERL",
    "title": "you need to dance",
    "genre": "H",
    "label": "",
    "time": "2021-12-03T11:05:04"
  },
  {
    "otitle": "(H) ELEKTRONS - joy",
    "artist": "ELEKTRONS",
    "title": "joy",
    "genre": "H",
    "label": "",
    "time": "2021-12-03T11:14:31"
  },
  {
    "otitle": "(W_H) DIGITAL AFRIKA - Asiko",
    "artist": "DIGITAL AFRIKA",
    "title": "Asiko",
    "genre": "W_H",
    "label": "",
    "time": "2021-12-03T11:23:20"
  },
  {
    "otitle": "(Disco) KATMANDU - the breaks UNIDISC",
    "artist": "KATMANDU",
    "title": "the breaks",
    "genre": "Disco",
    "label": "UNIDISC",
    "time": "2021-12-03T11:29:12"
  },
  {
    "otitle": "(Db) RONI SIZE - brown paper bag",
    "artist": "RONI SIZE",
    "title": "brown paper bag",
    "genre": "Db",
    "label": "",
    "time": "2021-12-03T11:41:43"
  },
  {
    "otitle": "(Dt) THE SIMONSOUND - between the wake and the sleep",
    "artist": "THE SIMONSOUND",
    "title": "between the wake and the sleep",
    "genre": "Dt",
    "label": "",
    "time": "2021-12-03T11:50:51"
  },
  {
    "otitle": "(E) LFO. - ..........WARP",
    "artist": "LFO.",
    "title": ".........",
    "genre": "E",
    "label": "WARP",
    "time": "2021-12-03T11:53:37"
  },
  {
    "otitle": "(Ro) THE RAMONES - surfin bird",
    "artist": "THE RAMONES",
    "title": "surfin bird",
    "genre": "Ro",
    "label": "",
    "time": "2021-12-03T11:57:49"
  },
  {
    "otitle": "PBB - Luckily We Still Have Music",
    "artist": "PBB",
    "title": "Luckily We Still Have Music",
    "genre": "BB - Luckily We Still Have Musi",
    "label": "",
    "time": "2021-12-03T12:00:25"
  },
  {
    "otitle": "(J) THE RONGETZ FOUNDATION - ny timbuctu",
    "artist": "THE RONGETZ FOUNDATION",
    "title": "ny timbuctu",
    "genre": "J",
    "label": "",
    "time": "2021-12-03T12:00:37"
  },
  {
    "otitle": "(W_H_N) HAILU MERGIA - ambasel (El Guincho club alize edit)",
    "artist": "HAILU MERGIA",
    "title": "ambasel (El Guincho club alize edit)",
    "genre": "W_H_N",
    "label": "",
    "time": "2021-12-03T12:08:11"
  },
  {
    "otitle": "(P_N) TIM PARIS - Zab (With Erika)",
    "artist": "TIM PARIS",
    "title": "Zab (With Erika)",
    "genre": "P_N",
    "label": "",
    "time": "2021-12-03T12:13:52"
  },
  {
    "otitle": "(P_N) TIM PARIS - Zab (With Erika)",
    "artist": "TIM PARIS",
    "title": "Zab (With Erika)",
    "genre": "P_N",
    "label": "",
    "time": "2021-12-03T12:23:00"
  },
  {
    "otitle": "(T) TARAN & LOMOV - Voltage _ OVUM",
    "artist": "TARAN & LOMOV",
    "title": "TARAN & LOMOV - Voltage",
    "genre": "T",
    "label": "OVUM",
    "time": "2021-12-03T12:26:15"
  },
  {
    "otitle": "PBB - Luckily We Still Have Music",
    "artist": "PBB",
    "title": "Luckily We Still Have Music",
    "genre": "BB - Luckily We Still Have Musi",
    "label": "",
    "time": "2021-12-03T12:31:51"
  },
  {
    "otitle": "(F) TURBULANCE - Runnin _ COOPERATION",
    "artist": "TURBULANCE",
    "title": "TURBULANCE - Runnin",
    "genre": "F",
    "label": "COOPERATION",
    "time": "2021-12-03T12:32:02"
  },
  {
    "otitle": "(H) LIZ TORRES - music JIVE",
    "artist": "LIZ TORRES",
    "title": "music",
    "genre": "H",
    "label": "JIVE",
    "time": "2021-12-03T12:37:33"
  },
  {
    "otitle": "(HH) SAUL WILLIAMS - la la la",
    "artist": "SAUL WILLIAMS",
    "title": "la la la",
    "genre": "HH",
    "label": "",
    "time": "2021-12-03T12:42:21"
  },
  {
    "otitle": "(F) THE POINTER SISTERS - yes we can can",
    "artist": "THE POINTER SISTERS",
    "title": "yes we can can",
    "genre": "F",
    "label": "",
    "time": "2021-12-03T12:44:57"
  },
  {
    "otitle": "(W) TETA LANDO - cecilia",
    "artist": "TETA LANDO",
    "title": "cecilia",
    "genre": "W",
    "label": "",
    "time": "2021-12-03T12:50:59"
  },
  {
    "otitle": "(Fr) DASHIELL HEDAYAT - Long Song For Zelda",
    "artist": "DASHIELL HEDAYAT",
    "title": "Long Song For Zelda",
    "genre": "Fr",
    "label": "",
    "time": "2021-12-03T12:54:39"
  },
  {
    "otitle": "(Fr) DASHIELL HEDAYAT - Long Song For Zelda",
    "artist": "DASHIELL HEDAYAT",
    "title": "Long Song For Zelda",
    "genre": "Fr",
    "label": "",
    "time": "2021-12-03T13:00:42"
  },
  {
    "otitle": "(P) SHAWN LEE - windy city",
    "artist": "SHAWN LEE",
    "title": "windy city",
    "genre": "P",
    "label": "",
    "time": "2021-12-03T13:02:20"
  },
  {
    "otitle": "(H) FIRST CHOICE - Let No Man Put Asunder (Dam Swindle Remix) _ SALSOUL",
    "artist": "FIRST CHOICE",
    "title": "FIRST CHOICE - Let No Man Put Asunder (Dam Swindle Remix)",
    "genre": "H",
    "label": "SALSOUL",
    "time": "2021-12-03T13:04:51"
  },
  {
    "otitle": "(D_N) TOKYO BLACK STAR - dance hall",
    "artist": "TOKYO BLACK STAR",
    "title": "dance hall",
    "genre": "D_N",
    "label": "",
    "time": "2021-12-03T13:12:31"
  },
  {
    "otitle": "(J) BOOGALOO - you gotta have freedom GAMM",
    "artist": "BOOGALOO",
    "title": "you gotta have freedom",
    "genre": "J",
    "label": "GAMM",
    "time": "2021-12-03T13:19:27"
  },
  {
    "otitle": "unknown or problem",
    "artist": "unknown or proble",
    "title": "unknown or problem",
    "genre": "nknown or proble",
    "label": "",
    "time": "2021-12-03T13:20:14"
  },
  {
    "otitle": "(E) SLUGABED - sun too bright turn it off",
    "artist": "SLUGABED",
    "title": "sun too bright turn it off",
    "genre": "E",
    "label": "",
    "time": "2021-12-03T13:24:42"
  },
  {
    "otitle": "(Db_N) HUGH HARDIE - Overture _ HOSPITAL",
    "artist": "HUGH HARDIE",
    "title": "HUGH HARDIE - Overture",
    "genre": "Db_N",
    "label": "HOSPITAL",
    "time": "2021-12-03T13:28:39"
  },
  {
    "otitle": "(Db) SOURCE DIRECT - Street Wars _ TEMPO SPEED",
    "artist": "SOURCE DIRECT",
    "title": "SOURCE DIRECT - Street Wars",
    "genre": "Db",
    "label": "TEMPO SPEED",
    "time": "2021-12-03T13:32:42"
  },
  {
    "otitle": "PBB - Luckily We Still Have Music",
    "artist": "PBB",
    "title": "Luckily We Still Have Music",
    "genre": "BB - Luckily We Still Have Musi",
    "label": "",
    "time": "2021-12-03T13:38:57"
  },
  {
    "otitle": "(H) TENTH AND PARKER - kool down DISORIENT",
    "artist": "TENTH AND PARKER",
    "title": "kool down",
    "genre": "H",
    "label": "DISORIENT",
    "time": "2021-12-03T13:39:38"
  },
  {
    "otitle": "(H) BRASSICA - splash",
    "artist": "BRASSICA",
    "title": "splash",
    "genre": "H",
    "label": "",
    "time": "2021-12-03T13:47:00"
  },
  {
    "otitle": "(Ra) SHA SHA - bad attitude",
    "artist": "SHA SHA",
    "title": "bad attitude",
    "genre": "Ra",
    "label": "",
    "time": "2021-12-03T13:52:07"
  },
  {
    "otitle": "(F) ESG - moody spaced out",
    "artist": "ESG",
    "title": "moody spaced out",
    "genre": "F",
    "label": "",
    "time": "2021-12-03T13:56:31"
  },
  {
    "otitle": "(HH) OBBA_SUPA_TO_AM_ - wot_u_chatting_bout_",
    "artist": "OBBA_SUPA_TO_AM_",
    "title": "wot_u_chatting_bout_",
    "genre": "HH",
    "label": "",
    "time": "2021-12-03T14:00:45"
  },
  {
    "otitle": "(N) LUNE TNS - the story entangles SUB VERSE",
    "artist": "LUNE TNS",
    "title": "the story entangles",
    "genre": "N",
    "label": "SUB VERSE",
    "time": "2021-12-03T14:04:24"
  },
  {
    "otitle": "(Dt) BEN MONO DUAL - suburban resident COMPOST",
    "artist": "BEN MONO DUAL",
    "title": "suburban resident",
    "genre": "Dt",
    "label": "COMPOST",
    "time": "2021-12-03T14:08:04"
  },
  {
    "otitle": "(Fr) ROBIN LEDUC - je casse tout",
    "artist": "ROBIN LEDUC",
    "title": "je casse tout",
    "genre": "Fr",
    "label": "",
    "time": "2021-12-03T14:14:20"
  },
  {
    "otitle": "PBB - Luckily We Still Have Music",
    "artist": "PBB",
    "title": "Luckily We Still Have Music",
    "genre": "BB - Luckily We Still Have Musi",
    "label": "",
    "time": "2021-12-03T14:17:31"
  },
  {
    "otitle": "(J) PLEASURE - jammin with pleasure",
    "artist": "PLEASURE",
    "title": "jammin with pleasure",
    "genre": "J",
    "label": "",
    "time": "2021-12-03T14:17:49"
  },
  {
    "otitle": "(F_N) IKEBE SHAKEDOWN - no name bar",
    "artist": "IKEBE SHAKEDOWN",
    "title": "no name bar",
    "genre": "F_N",
    "label": "",
    "time": "2021-12-03T14:20:09"
  },
  {
    "otitle": "(Db_N) SCAPE - Spirit World (Soul Intents Spirit Of Speed Remix) _ DOPE PLATES",
    "artist": "SCAPE",
    "title": "SCAPE - Spirit World (Soul Intents Spirit Of Speed Remix)",
    "genre": "Db_N",
    "label": "DOPE PLATES",
    "time": "2021-12-03T14:23:37"
  },
  {
    "otitle": "(T) MICROTHOL & K 1 - Binary Systems",
    "artist": "MICROTHOL & K 1",
    "title": "Binary Systems",
    "genre": "T",
    "label": "",
    "time": "2021-12-03T14:31:31"
  },
  {
    "otitle": "PBB - Luckily We Still Have Music",
    "artist": "PBB",
    "title": "Luckily We Still Have Music",
    "genre": "BB - Luckily We Still Have Musi",
    "label": "",
    "time": "2021-12-03T14:35:23"
  },
  {
    "otitle": "(H) PARISIAN SOUL - Diamant Bleu (Parisian Soul Mix) _ LOCAL TALK",
    "artist": "PARISIAN SOUL",
    "title": "PARISIAN SOUL - Diamant Bleu (Parisian Soul Mix)",
    "genre": "H",
    "label": "LOCAL TALK",
    "time": "2021-12-03T14:35:46"
  },
  {
    "otitle": "(T) EMBRACE THE FUTURE EP - 430 WEST",
    "artist": "EMBRACE THE FUTURE EP",
    "title": "430",
    "genre": "T",
    "label": "WEST",
    "time": "2021-12-03T14:41:46"
  },
  {
    "otitle": "(HH) BEASTY BOYS - shazam",
    "artist": "BEASTY BOYS",
    "title": "shazam",
    "genre": "HH",
    "label": "",
    "time": "2021-12-03T14:46:41"
  },
  {
    "otitle": "(F) GERALDO PINO & THE HEARTBEATS - heavy, heavy, heavy",
    "artist": "GERALDO PINO & THE HEARTBEATS",
    "title": "heavy, heavy, heavy",
    "genre": "F",
    "label": "",
    "time": "2021-12-03T14:49:07"
  },
  {
    "otitle": "(F) GERALDO PINO & THE HEARTBEATS - heavy, heavy, heavy",
    "artist": "GERALDO PINO & THE HEARTBEATS",
    "title": "heavy, heavy, heavy",
    "genre": "F",
    "label": "",
    "time": "2021-12-03T14:52:55"
  },
  {
    "otitle": "(R) EARLY B - girls dem sexy",
    "artist": "EARLY B",
    "title": "girls dem sexy",
    "genre": "R",
    "label": "",
    "time": "2021-12-03T14:55:42"
  },
  {
    "otitle": "(Fr) ENCRE - air CLAPPING MUSIC",
    "artist": "ENCRE",
    "title": "air",
    "genre": "Fr",
    "label": "CLAPPING MUSIC",
    "time": "2021-12-03T14:59:33"
  },
  {
    "otitle": "(E) MAXIME DANGLES - Pariscope _ SKRYPTOM",
    "artist": "MAXIME DANGLES",
    "title": "MAXIME DANGLES - Pariscope",
    "genre": "E",
    "label": "SKRYPTOM",
    "time": "2021-12-03T15:02:26"
  },
  {
    "otitle": "PBB - Luckily We Still Have Music",
    "artist": "PBB",
    "title": "Luckily We Still Have Music",
    "genre": "BB - Luckily We Still Have Musi",
    "label": "",
    "time": "2021-12-03T15:06:36"
  },
  {
    "otitle": "(H) ARTIST CODE 4B594F (KYODAI) - Alma",
    "artist": "ARTIST CODE 4B594F (KYODAI)",
    "title": "Alma",
    "genre": "H",
    "label": "",
    "time": "2021-12-03T15:06:55"
  },
  {
    "otitle": "(H) ARTIST CODE 4B594F (KYODAI) - Alma",
    "artist": "ARTIST CODE 4B594F (KYODAI)",
    "title": "Alma",
    "genre": "H",
    "label": "",
    "time": "2021-12-03T15:09:40"
  },
  {
    "otitle": "(T) NEW WORLD AQUARIUM - monkey world",
    "artist": "NEW WORLD AQUARIUM",
    "title": "monkey world",
    "genre": "T",
    "label": "",
    "time": "2021-12-03T15:15:04"
  },
  {
    "otitle": "(W) EBO TAYLOR - aboa kyirbin",
    "artist": "EBO TAYLOR",
    "title": "aboa kyirbin",
    "genre": "W",
    "label": "",
    "time": "2021-12-03T15:19:53"
  },
  {
    "otitle": "(F) JOSPEH MALIK - take a left",
    "artist": "JOSPEH MALIK",
    "title": "take a left",
    "genre": "F",
    "label": "",
    "time": "2021-12-03T15:25:01"
  },
  {
    "otitle": "(HH) MANTRONIX - king of the beats",
    "artist": "MANTRONIX",
    "title": "king of the beats",
    "genre": "HH",
    "label": "",
    "time": "2021-12-03T15:28:35"
  },
  {
    "otitle": "(N) LAMBCHOP - the daily growl CITY SLANG",
    "artist": "LAMBCHOP",
    "title": "the daily growl",
    "genre": "N",
    "label": "CITY SLANG",
    "time": "2021-12-03T15:33:58"
  },
  {
    "otitle": "(N) DJ LOGIC - drone ROPEADOPE",
    "artist": "DJ LOGIC",
    "title": "drone",
    "genre": "N",
    "label": "ROPEADOPE",
    "time": "2021-12-03T15:40:32"
  },
  {
    "otitle": "(Ro) NEW ORDER - blue monday FACTORY",
    "artist": "NEW ORDER",
    "title": "blue monday",
    "genre": "Ro",
    "label": "FACTORY",
    "time": "2021-12-03T15:44:47"
  },
  {
    "otitle": "PBB - Luckily We Still Have Music",
    "artist": "PBB",
    "title": "Luckily We Still Have Music",
    "genre": "BB - Luckily We Still Have Musi",
    "label": "",
    "time": "2021-12-03T15:52:14"
  },
  {
    "otitle": "(J) BOKANI DYER - Ke Nako _ BROWNSWOOD",
    "artist": "BOKANI DYER",
    "title": "BOKANI DYER - Ke Nako",
    "genre": "J",
    "label": "BROWNSWOOD",
    "time": "2021-12-03T15:52:31"
  },
  {
    "otitle": "(J_N) CLEVELAND EATON - all your lover all day all night",
    "artist": "CLEVELAND EATON",
    "title": "all your lover all day all night",
    "genre": "J_N",
    "label": "",
    "time": "2021-12-03T15:59:10"
  },
  {
    "otitle": "(Beats_N) SLEEPY RICH - Solaris _ ILLIAN TAPE",
    "artist": "SLEEPY RICH",
    "title": "SLEEPY RICH - Solaris",
    "genre": "Beats_N",
    "label": "ILLIAN TAPE",
    "time": "2021-12-03T16:08:33"
  },
  {
    "otitle": "(HH) LORAINE JAMES - We're building something new",
    "artist": "LORAINE JAMES",
    "title": "We're building something new",
    "genre": "HH",
    "label": "",
    "time": "2021-12-03T16:13:40"
  },
  {
    "otitle": "PBB - Luckily We Still Have Music",
    "artist": "PBB",
    "title": "Luckily We Still Have Music",
    "genre": "BB - Luckily We Still Have Musi",
    "label": "",
    "time": "2021-12-03T16:16:05"
  },
  {
    "otitle": "(E) COLLATERAL INTELLIGENCE - Maribou _ GATED",
    "artist": "COLLATERAL INTELLIGENCE",
    "title": "COLLATERAL INTELLIGENCE - Maribou",
    "genre": "E",
    "label": "GATED",
    "time": "2021-12-03T16:16:34"
  },
  {
    "otitle": "(H) LOU 2 - freaky",
    "artist": "LOU 2",
    "title": "freaky",
    "genre": "H",
    "label": "",
    "time": "2021-12-03T16:21:39"
  },
  {
    "otitle": "(HH) STATIK SELEKTAH - what can we do (Parts 1)",
    "artist": "STATIK SELEKTAH",
    "title": "what can we do (Parts 1)",
    "genre": "HH",
    "label": "",
    "time": "2021-12-03T16:32:15"
  },
  {
    "otitle": "(S) CLARENCE SMITH - sometimes i feel like a motherless child",
    "artist": "CLARENCE SMITH",
    "title": "sometimes i feel like a motherless child",
    "genre": "S",
    "label": "",
    "time": "2021-12-03T16:35:50"
  },
  {
    "otitle": "(R) WAYNE SMITH - under me sleng teng",
    "artist": "WAYNE SMITH",
    "title": "under me sleng teng",
    "genre": "R",
    "label": "",
    "time": "2021-12-03T16:40:57"
  },
  {
    "otitle": "(P) SIMON SAYS - late at night",
    "artist": "SIMON SAYS",
    "title": "late at night",
    "genre": "P",
    "label": "",
    "time": "2021-12-03T16:45:07"
  },
  {
    "otitle": "(Ro) JACK ADAPTOR - chocolat malted",
    "artist": "JACK ADAPTOR",
    "title": "chocolat malted",
    "genre": "Ro",
    "label": "",
    "time": "2021-12-03T16:49:26"
  },
  {
    "otitle": "(H) HONEY DIJON - Downtown _ CLASSIC MUSIC COMPANY",
    "artist": "HONEY DIJON",
    "title": "HONEY DIJON - Downtown",
    "genre": "H",
    "label": "CLASSIC MUSIC COMPANY",
    "time": "2021-12-03T16:51:51"
  },
  {
    "otitle": "PBB - Luckily We Still Have Music",
    "artist": "PBB",
    "title": "Luckily We Still Have Music",
    "genre": "BB - Luckily We Still Have Musi",
    "label": "",
    "time": "2021-12-03T16:57:58"
  },
  {
    "otitle": "(P_N) NICK DRAKE - black eyed dog",
    "artist": "NICK DRAKE",
    "title": "black eyed dog",
    "genre": "P_N",
    "label": "",
    "time": "2021-12-03T16:58:33"
  },
  {
    "otitle": "(Jup) LOUIS PRIMA - Hey Boy! Hey Girl!",
    "artist": "LOUIS PRIMA",
    "title": "Hey Boy! Hey Girl!",
    "genre": "Jup",
    "label": "",
    "time": "2021-12-03T17:01:55"
  },
  {
    "otitle": "(E) LAURENT GARNIER - greed remix F COMM",
    "artist": "LAURENT GARNIER",
    "title": "greed remix",
    "genre": "E",
    "label": "F COMM",
    "time": "2021-12-03T17:04:38"
  },
  {
    "otitle": "(H_N) DJ OIL - Ridetheblind",
    "artist": "DJ OIL",
    "title": "Ridetheblind",
    "genre": "H_N",
    "label": "",
    "time": "2021-12-03T17:11:06"
  },
  {
    "otitle": "(T) JEFF MILLS & THE ZANZA 21 - When The Time Is Right _ AXIS",
    "artist": "JEFF MILLS & THE ZANZA 21",
    "title": "JEFF MILLS & THE ZANZA 21 - When The Time Is Right",
    "genre": "T",
    "label": "AXIS",
    "time": "2021-12-03T17:16:08"
  },
  {
    "otitle": "PBB - Luckily We Still Have Music",
    "artist": "PBB",
    "title": "Luckily We Still Have Music",
    "genre": "BB - Luckily We Still Have Musi",
    "label": "",
    "time": "2021-12-03T17:23:10"
  },
  {
    "otitle": "(H) ADANA TWINS - Everyday",
    "artist": "ADANA TWINS",
    "title": "Everyday",
    "genre": "H",
    "label": "",
    "time": "2021-12-03T17:23:27"
  },
  {
    "otitle": "(H) FRANCESCO ROSSI - paper aeroplane",
    "artist": "FRANCESCO ROSSI",
    "title": "paper aeroplane",
    "genre": "H",
    "label": "",
    "time": "2021-12-03T17:30:17"
  },
  {
    "otitle": "(Spain) ANTONIO GONZALEZ  'EL PESCAILLA' - Levantate",
    "artist": "ANTONIO GONZALEZ  'EL PESCAILLA'",
    "title": "Levantate",
    "genre": "Spain",
    "label": "",
    "time": "2021-12-03T17:37:37"
  },
  {
    "otitle": "(F) JINGO - fever",
    "artist": "JINGO",
    "title": "fever",
    "genre": "F",
    "label": "",
    "time": "2021-12-03T17:39:51"
  },
  {
    "otitle": "(HH) DAN LE SAC Vs SCROOBIUS PIP - heroism",
    "artist": "DAN LE SAC Vs SCROOBIUS PIP",
    "title": "heroism",
    "genre": "HH",
    "label": "",
    "time": "2021-12-03T17:46:30"
  },
  {
    "otitle": "(N) FELIX LABAND - whistling in tongues",
    "artist": "FELIX LABAND",
    "title": "whistling in tongues",
    "genre": "N",
    "label": "",
    "time": "2021-12-03T17:50:03"
  },
  {
    "otitle": "(Dt) JAMIE CULLUM VS DAN THE AUTOMATOR - get your way remix",
    "artist": "JAMIE CULLUM VS DAN THE AUTOMATOR",
    "title": "get your way remix",
    "genre": "Dt",
    "label": "",
    "time": "2021-12-03T17:54:18"
  },
  {
    "otitle": "(Ro) GISLI - can you make me right",
    "artist": "GISLI",
    "title": "can you make me right",
    "genre": "Ro",
    "label": "",
    "time": "2021-12-03T17:57:58"
  },
  {
    "otitle": "PBB - Luckily We Still Have Music",
    "artist": "PBB",
    "title": "Luckily We Still Have Music",
    "genre": "BB - Luckily We Still Have Musi",
    "label": "",
    "time": "2021-12-03T18:01:15"
  },
  {
    "otitle": "(H) CJ BOLLAND - sugas is sweeter",
    "artist": "CJ BOLLAND",
    "title": "sugas is sweeter",
    "genre": "H",
    "label": "",
    "time": "2021-12-03T18:01:50"
  },
  {
    "otitle": "(H) 10LEC6 - bone bame (Waajeed's Bone Dub)",
    "artist": "10LEC6",
    "title": "bone bame (Waajeed's Bone Dub)",
    "genre": "H",
    "label": "",
    "time": "2021-12-03T18:07:14"
  },
  {
    "otitle": "(F) RADIO CITIZEN - opium",
    "artist": "RADIO CITIZEN",
    "title": "opium",
    "genre": "F",
    "label": "",
    "time": "2021-12-03T18:13:18"
  },
  {
    "otitle": "(F) THE STANCE BROTHERS - Roll Call",
    "artist": "THE STANCE BROTHERS",
    "title": "Roll Call",
    "genre": "F",
    "label": "",
    "time": "2021-12-03T18:17:28"
  },
  {
    "otitle": "(H_N) ANGEL A - let go",
    "artist": "ANGEL A",
    "title": "let go",
    "genre": "H_N",
    "label": "",
    "time": "2021-12-03T18:21:25"
  },
  {
    "otitle": "PBB - Luckily We Still Have Music",
    "artist": "PBB",
    "title": "Luckily We Still Have Music",
    "genre": "BB - Luckily We Still Have Musi",
    "label": "",
    "time": "2021-12-03T18:30:30"
  },
  {
    "otitle": "(Fr) AGORIA - wrong line",
    "artist": "AGORIA",
    "title": "wrong line",
    "genre": "Fr",
    "label": "",
    "time": "2021-12-03T18:30:36"
  },
  {
    "otitle": "(P) ANTHONY HAMILTON - freedom",
    "artist": "ANTHONY HAMILTON",
    "title": "freedom",
    "genre": "P",
    "label": "",
    "time": "2021-12-03T18:35:02"
  },
  {
    "otitle": "(T) VINCE WATSON - Forever",
    "artist": "VINCE WATSON",
    "title": "Forever",
    "genre": "T",
    "label": "",
    "time": "2021-12-03T18:39:06"
  },
  {
    "otitle": "PBB - Luckily We Still Have Music",
    "artist": "PBB",
    "title": "Luckily We Still Have Music",
    "genre": "BB - Luckily We Still Have Musi",
    "label": "",
    "time": "2021-12-03T18:46:15"
  },
  {
    "otitle": "(HH) TRINITY - interview",
    "artist": "TRINITY",
    "title": "interview",
    "genre": "HH",
    "label": "",
    "time": "2021-12-03T18:46:38"
  },
  {
    "otitle": "(R) NICODEMUS - nicko dread",
    "artist": "NICODEMUS",
    "title": "nicko dread",
    "genre": "R",
    "label": "",
    "time": "2021-12-03T18:49:32"
  },
  {
    "otitle": "(J) MINI GROOVE ORCHESTRA - are you minigrooved",
    "artist": "MINI GROOVE ORCHESTRA",
    "title": "are you minigrooved",
    "genre": "J",
    "label": "",
    "time": "2021-12-03T18:53:07"
  },
  {
    "otitle": "PBB - Luckily We Still Have Music",
    "artist": "PBB",
    "title": "Luckily We Still Have Music",
    "genre": "BB - Luckily We Still Have Musi",
    "label": "",
    "time": "2021-12-03T18:57:57"
  },
  {
    "otitle": "(H) CULTURED PEARLS - mother earth (Hoffs Optimistic House Edit)",
    "artist": "CULTURED PEARLS",
    "title": "mother earth (Hoffs Optimistic House Edit)",
    "genre": "H",
    "label": "",
    "time": "2021-12-03T18:59:25"
  },
  {
    "otitle": "(H) DEE DEE BRIDGWATER - children go round",
    "artist": "DEE DEE BRIDGWATER",
    "title": "children go round",
    "genre": "H",
    "label": "",
    "time": "2021-12-03T19:08:18"
  },
  {
    "otitle": "(F) SKULL SNAPS - my hang up is you",
    "artist": "SKULL SNAPS",
    "title": "my hang up is you",
    "genre": "F",
    "label": "",
    "time": "2021-12-03T19:16:11"
  },
  {
    "otitle": "(F) HOT 8 BRASS - Get Up",
    "artist": "HOT 8 BRASS",
    "title": "Get Up",
    "genre": "F",
    "label": "",
    "time": "2021-12-03T19:20:08"
  },
  {
    "otitle": "(H_N) ISOLEE - allowance",
    "artist": "ISOLEE",
    "title": "allowance",
    "genre": "H_N",
    "label": "",
    "time": "2021-12-03T19:25:07"
  },
  {
    "otitle": "PBB - Luckily We Still Have Music",
    "artist": "PBB",
    "title": "Luckily We Still Have Music",
    "genre": "BB - Luckily We Still Have Musi",
    "label": "",
    "time": "2021-12-03T19:31:51"
  },
  {
    "otitle": "(P_E) OUT COLD - sorrow (The Invisible Remix)",
    "artist": "OUT COLD",
    "title": "sorrow (The Invisible Remix)",
    "genre": "P_E",
    "label": "",
    "time": "2021-12-03T19:32:03"
  },
  {
    "otitle": "(P) ANTIPOP - vampy",
    "artist": "ANTIPOP",
    "title": "vampy",
    "genre": "P",
    "label": "",
    "time": "2021-12-03T19:37:44"
  },
  {
    "otitle": "(F) LIGHTNING HEAD - The N.P.G. (Romanowski Rmx) _ TRU THOUGHTS",
    "artist": "LIGHTNING HEAD",
    "title": "LIGHTNING HEAD - The N.P.G. (Romanowski Rmx)",
    "genre": "F",
    "label": "TRU THOUGHTS",
    "time": "2021-12-03T19:40:26"
  },
  {
    "otitle": "PBB - Luckily We Still Have Music",
    "artist": "PBB",
    "title": "Luckily We Still Have Music",
    "genre": "BB - Luckily We Still Have Musi",
    "label": "",
    "time": "2021-12-03T19:45:27"
  },
  {
    "otitle": "(HH) THINK TWICE - stars",
    "artist": "THINK TWICE",
    "title": "stars",
    "genre": "HH",
    "label": "",
    "time": "2021-12-03T19:45:45"
  },
  {
    "otitle": "(Bra) ABILIO MANOEL - luiza manequim",
    "artist": "ABILIO MANOEL",
    "title": "luiza manequim",
    "genre": "Bra",
    "label": "",
    "time": "2021-12-03T19:49:13"
  },
  {
    "otitle": "(J) PETE PHILLY AND PERQUISITE - beleiver",
    "artist": "PETE PHILLY AND PERQUISITE",
    "title": "beleiver",
    "genre": "J",
    "label": "",
    "time": "2021-12-03T19:52:25"
  },
  {
    "otitle": "PBB - Luckily We Still Have Music",
    "artist": "PBB",
    "title": "Luckily We Still Have Music",
    "genre": "BB - Luckily We Still Have Musi",
    "label": "",
    "time": "2021-12-03T19:57:21"
  },
  {
    "otitle": "(H) STEVIE V - jealosy MERCURY",
    "artist": "STEVIE V",
    "title": "jealosy",
    "genre": "H",
    "label": "MERCURY",
    "time": "2021-12-03T19:58:02"
  },
  {
    "otitle": "(H) WHITE NIGHT - gonna jack INDIGO",
    "artist": "WHITE NIGHT",
    "title": "gonna jack",
    "genre": "H",
    "label": "INDIGO",
    "time": "2021-12-03T20:05:36"
  },
  {
    "otitle": "(F) LA FORMULE DU BARON - la gibouille",
    "artist": "LA FORMULE DU BARON",
    "title": "la gibouille",
    "genre": "F",
    "label": "",
    "time": "2021-12-03T20:11:46"
  },
  {
    "otitle": "(F) HERBIE HANCOCK - rock it CBS",
    "artist": "HERBIE HANCOCK",
    "title": "rock it",
    "genre": "F",
    "label": "CBS",
    "time": "2021-12-03T20:15:37"
  },
  {
    "otitle": "(T_N) D MAY - (from acetate...never released)",
    "artist": "D MAY",
    "title": "(from acetate...never released)",
    "genre": "T_N",
    "label": "",
    "time": "2021-12-03T20:20:57"
  },
  {
    "otitle": "PBB - Luckily We Still Have Music",
    "artist": "PBB",
    "title": "Luckily We Still Have Music",
    "genre": "BB - Luckily We Still Have Musi",
    "label": "",
    "time": "2021-12-03T20:24:56"
  },
  {
    "otitle": "(Ro) LONG VIEW - when you sleep",
    "artist": "LONG VIEW",
    "title": "when you sleep",
    "genre": "Ro",
    "label": "",
    "time": "2021-12-03T20:25:43"
  },
  {
    "otitle": "(Fr) MICHEL POLNAREFF - hey you woman",
    "artist": "MICHEL POLNAREFF",
    "title": "hey you woman",
    "genre": "Fr",
    "label": "",
    "time": "2021-12-03T20:29:46"
  },
  {
    "otitle": "(H) BONOBO - Rosewood _ NINJA TUNE",
    "artist": "BONOBO",
    "title": "BONOBO - Rosewood",
    "genre": "H",
    "label": "NINJA TUNE",
    "time": "2021-12-03T20:34:59"
  },
  {
    "otitle": "PBB - Luckily We Still Have Music",
    "artist": "PBB",
    "title": "Luckily We Still Have Music",
    "genre": "BB - Luckily We Still Have Musi",
    "label": "",
    "time": "2021-12-03T20:39:02"
  },
  {
    "otitle": "(Db) D KAY AND MAT - uncovered funk",
    "artist": "D KAY AND MAT",
    "title": "uncovered funk",
    "genre": "Db",
    "label": "",
    "time": "2021-12-03T20:39:26"
  },
  {
    "otitle": "(W) THE WHITEFIELD BROTHERS - Sad Nile",
    "artist": "THE WHITEFIELD BROTHERS",
    "title": "Sad Nile",
    "genre": "W",
    "label": "",
    "time": "2021-12-03T20:44:45"
  },
  {
    "otitle": "(J) THE DEIRDRE WILSON TABAC - i can't keep from crying sometimes",
    "artist": "THE DEIRDRE WILSON TABAC",
    "title": "i can't keep from crying sometimes",
    "genre": "J",
    "label": "",
    "time": "2021-12-03T20:48:31"
  },
  {
    "otitle": "PBB - Luckily We Still Have Music",
    "artist": "PBB",
    "title": "Luckily We Still Have Music",
    "genre": "BB - Luckily We Still Have Musi",
    "label": "",
    "time": "2021-12-03T20:51:50"
  },
  {
    "otitle": "(H) FAST EDDIE - acid thunder DJ INTERNATIONAL",
    "artist": "FAST EDDIE",
    "title": "acid thunder",
    "genre": "H",
    "label": "DJ INTERNATIONAL",
    "time": "2021-12-03T20:52:43"
  },
  {
    "otitle": "(T) THE HORRORIST - Lay On Me",
    "artist": "THE HORRORIST",
    "title": "Lay On Me",
    "genre": "T",
    "label": "",
    "time": "2021-12-03T20:57:10"
  },
  {
    "otitle": "PBB - Luckily We Still Have Music",
    "artist": "PBB",
    "title": "Luckily We Still Have Music",
    "genre": "BB - Luckily We Still Have Musi",
    "label": "",
    "time": "2021-12-03T21:01:15"
  },
  {
    "otitle": "(H) JOESKI - my english lover TRAX",
    "artist": "JOESKI",
    "title": "my english lover",
    "genre": "H",
    "label": "TRAX",
    "time": "2021-12-03T21:01:51"
  },
  {
    "otitle": "(H) DJ DEEON - house o matic",
    "artist": "DJ DEEON",
    "title": "house o matic",
    "genre": "H",
    "label": "",
    "time": "2021-12-03T21:14:09"
  },
  {
    "otitle": "(F) SYREETA - can t shake your love MOTOWN",
    "artist": "SYREETA",
    "title": "can t shake your love",
    "genre": "F",
    "label": "MOTOWN",
    "time": "2021-12-03T21:18:24"
  },
  {
    "otitle": "(H_N) 2AMFM - give this world",
    "artist": "2AMFM",
    "title": "give this world",
    "genre": "H_N",
    "label": "",
    "time": "2021-12-03T21:23:50"
  },
  {
    "otitle": "(T) A GUY CALLED GERALD - vodoo ray DECONSTRUCTION",
    "artist": "A GUY CALLED GERALD",
    "title": "vodoo ray",
    "genre": "T",
    "label": "DECONSTRUCTION",
    "time": "2021-12-03T21:30:14"
  },
  {
    "otitle": "PBB - Luckily We Still Have Music",
    "artist": "PBB",
    "title": "Luckily We Still Have Music",
    "genre": "BB - Luckily We Still Have Musi",
    "label": "",
    "time": "2021-12-03T21:34:25"
  },
  {
    "otitle": "(Bb_Ra) TOUCHY SUBJECT - general",
    "artist": "TOUCHY SUBJECT",
    "title": "general",
    "genre": "Bb_Ra",
    "label": "",
    "time": "2021-12-03T21:34:37"
  },
  {
    "otitle": "(HH) NOMINE - 99 Aachen",
    "artist": "NOMINE",
    "title": "99 Aachen",
    "genre": "HH",
    "label": "",
    "time": "2021-12-03T21:38:18"
  },
  {
    "otitle": "(D) BOB MARLEY - rebel music",
    "artist": "BOB MARLEY",
    "title": "rebel music",
    "genre": "D",
    "label": "",
    "time": "2021-12-03T21:41:58"
  },
  {
    "otitle": "(J) ANTHONY JOSEPH - Calling England Home _ HEAVENLY SWEETNESS",
    "artist": "ANTHONY JOSEPH",
    "title": "ANTHONY JOSEPH - Calling England Home",
    "genre": "J",
    "label": "HEAVENLY SWEETNESS",
    "time": "2021-12-03T21:52:07"
  },
  {
    "otitle": "PBB - Luckily We Still Have Music",
    "artist": "PBB",
    "title": "Luckily We Still Have Music",
    "genre": "BB - Luckily We Still Have Musi",
    "label": "",
    "time": "2021-12-03T21:58:13"
  },
  {
    "otitle": "(P) XERAC - sexfloor shakers",
    "artist": "XERAC",
    "title": "sexfloor shakers",
    "genre": "P",
    "label": "",
    "time": "2021-12-03T21:58:42"
  },
  {
    "otitle": "(Ro) BIKINI KILL - capri pants",
    "artist": "BIKINI KILL",
    "title": "capri pants",
    "genre": "Ro",
    "label": "",
    "time": "2021-12-03T22:01:36"
  },
  {
    "otitle": "PBB - Luckily We Still Have Music",
    "artist": "PBB",
    "title": "Luckily We Still Have Music",
    "genre": "BB - Luckily We Still Have Musi",
    "label": "",
    "time": "2021-12-03T22:03:15"
  },
  {
    "otitle": "(H) TEE MAMGO - music for molly",
    "artist": "TEE MAMGO",
    "title": "music for molly",
    "genre": "H",
    "label": "",
    "time": "2021-12-03T22:03:45"
  },
  {
    "otitle": "(T) STEROPLEXX - rita (Paul Nazca rmx)",
    "artist": "STEROPLEXX",
    "title": "rita (Paul Nazca rmx)",
    "genre": "T",
    "label": "",
    "time": "2021-12-03T22:10:42"
  },
  {
    "otitle": "(F) ROY HAYES - aragon",
    "artist": "ROY HAYES",
    "title": "aragon",
    "genre": "F",
    "label": "",
    "time": "2021-12-03T22:19:48"
  },
  {
    "otitle": "(Bb_N) THIRD SON - avril",
    "artist": "THIRD SON",
    "title": "avril",
    "genre": "Bb_N",
    "label": "",
    "time": "2021-12-03T22:22:32"
  },
  {
    "otitle": "(T) STERAC - Aeras",
    "artist": "STERAC",
    "title": "Aeras",
    "genre": "T",
    "label": "",
    "time": "2021-12-03T22:28:35"
  },
  {
    "otitle": "PBB - Luckily We Still Have Music",
    "artist": "PBB",
    "title": "Luckily We Still Have Music",
    "genre": "BB - Luckily We Still Have Musi",
    "label": "",
    "time": "2021-12-03T22:34:07"
  },
  {
    "otitle": "(Bb_T) SPECIAL REQUEST - Morning Ritual",
    "artist": "SPECIAL REQUEST",
    "title": "Morning Ritual",
    "genre": "Bb_T",
    "label": "",
    "time": "2021-12-03T22:34:37"
  },
  {
    "otitle": "(HH) THE JUGGAKNOTS - this morning MATADOR",
    "artist": "THE JUGGAKNOTS",
    "title": "this morning",
    "genre": "HH",
    "label": "MATADOR",
    "time": "2021-12-03T22:41:36"
  },
  {
    "otitle": "(W) EKAMBI BRILLIANT - africa africa",
    "artist": "EKAMBI BRILLIANT",
    "title": "africa africa",
    "genre": "W",
    "label": "",
    "time": "2021-12-03T22:45:24"
  },
  {
    "otitle": "(T) JEFF MILLS & THE ZANZA 21 - When The Time Is Right _ AXIS",
    "artist": "JEFF MILLS & THE ZANZA 21",
    "title": "JEFF MILLS & THE ZANZA 21 - When The Time Is Right",
    "genre": "T",
    "label": "AXIS",
    "time": "2021-12-03T22:47:32"
  },
  {
    "otitle": "PBB - Luckily We Still Have Music",
    "artist": "PBB",
    "title": "Luckily We Still Have Music",
    "genre": "BB - Luckily We Still Have Musi",
    "label": "",
    "time": "2021-12-03T22:54:32"
  },
  {
    "otitle": "(Ro) JAMES WHITE - contort yourself ZE",
    "artist": "JAMES WHITE",
    "title": "contort yourself",
    "genre": "Ro",
    "label": "ZE",
    "time": "2021-12-03T22:54:44"
  },
  {
    "otitle": "(Ro) MARTIN CREED - fuck off",
    "artist": "MARTIN CREED",
    "title": "fuck off",
    "genre": "Ro",
    "label": "",
    "time": "2021-12-03T22:57:45"
  },
  {
    "otitle": "PBB - Luckily We Still Have Music",
    "artist": "PBB",
    "title": "Luckily We Still Have Music",
    "genre": "BB - Luckily We Still Have Musi",
    "label": "",
    "time": "2021-12-03T22:58:50"
  },
  {
    "otitle": "(H) GHERKIN JERKS - acid indigestion GHERKIN",
    "artist": "GHERKIN JERKS",
    "title": "acid indigestion",
    "genre": "H",
    "label": "GHERKIN",
    "time": "2021-12-03T22:59:32"
  },
  {
    "otitle": "(H) GABRIELE POSO - Black Sand",
    "artist": "GABRIELE POSO",
    "title": "Black Sand",
    "genre": "H",
    "label": "",
    "time": "2021-12-03T23:04:00"
  },
  {
    "otitle": "(F) EDDIE LANG - gonna make you eat my words",
    "artist": "EDDIE LANG",
    "title": "gonna make you eat my words",
    "genre": "F",
    "label": "",
    "time": "2021-12-03T23:09:26"
  },
  {
    "otitle": "(H_N) INTROBEATZ - Night Vision",
    "artist": "INTROBEATZ",
    "title": "Night Vision",
    "genre": "H_N",
    "label": "",
    "time": "2021-12-03T23:12:04"
  },
  {
    "otitle": "(T) D I E - other people CLONE",
    "artist": "D I E",
    "title": "other people",
    "genre": "T",
    "label": "CLONE",
    "time": "2021-12-03T23:19:43"
  },
  {
    "otitle": "PBB - Luckily We Still Have Music",
    "artist": "PBB",
    "title": "Luckily We Still Have Music",
    "genre": "BB - Luckily We Still Have Musi",
    "label": "",
    "time": "2021-12-03T23:24:47"
  },
  {
    "otitle": "(HH) THE GIFT OF GAB - the writz",
    "artist": "THE GIFT OF GAB",
    "title": "the writz",
    "genre": "HH",
    "label": "",
    "time": "2021-12-03T23:25:06"
  },
  {
    "otitle": "(HH) YGG - strikers",
    "artist": "YGG",
    "title": "strikers",
    "genre": "HH",
    "label": "",
    "time": "2021-12-03T23:28:41"
  },
  {
    "otitle": "(D) MAX - you may die in the desert",
    "artist": "MAX",
    "title": "you may die in the desert",
    "genre": "D",
    "label": "",
    "time": "2021-12-03T23:32:23"
  },
  {
    "otitle": "(H) GROOVE BOYS PROJECT - Something Special _ AMSEM",
    "artist": "GROOVE BOYS PROJECT",
    "title": "GROOVE BOYS PROJECT - Something Special",
    "genre": "H",
    "label": "AMSEM",
    "time": "2021-12-03T23:36:33"
  },
  {
    "otitle": "PBB - Luckily We Still Have Music",
    "artist": "PBB",
    "title": "Luckily We Still Have Music",
    "genre": "BB - Luckily We Still Have Musi",
    "label": "",
    "time": "2021-12-03T23:43:38"
  },
  {
    "otitle": "(Ro) THESE BONES - toxic",
    "artist": "THESE BONES",
    "title": "toxic",
    "genre": "Ro",
    "label": "",
    "time": "2021-12-03T23:43:51"
  },
  {
    "otitle": "(Ro) BIGOTT - I Love Monkeys",
    "artist": "BIGOTT",
    "title": "I Love Monkeys",
    "genre": "Ro",
    "label": "",
    "time": "2021-12-03T23:47:03"
  },
  {
    "otitle": "PBB - Luckily We Still Have Music",
    "artist": "PBB",
    "title": "Luckily We Still Have Music",
    "genre": "BB - Luckily We Still Have Musi",
    "label": "",
    "time": "2021-12-03T23:49:18"
  },
  {
    "otitle": "(H) K HAND - i do  ACACIA",
    "artist": "K HAND",
    "title": "i do",
    "genre": "H",
    "label": "ACACIA",
    "time": "2021-12-03T23:49:36"
  },
  {
    "otitle": "(T) MODULAR EXPANSION - Cubes",
    "artist": "MODULAR EXPANSION",
    "title": "Cubes",
    "genre": "T",
    "label": "",
    "time": "2021-12-03T23:54:55"
  },
  {
    "otitle": "(S) GUY MORRIS - hot pants party",
    "artist": "GUY MORRIS",
    "title": "hot pants party",
    "genre": "S",
    "label": "",
    "time": "2021-12-03T23:59:05"
  }
]